volumentations/__init__.py
volumentations/random_utils.py
volumentations/augmentations/__init__.py
volumentations/augmentations/functional.py
volumentations/augmentations/transforms.py
volumentations/core/__init__.py
volumentations/core/composition.py
volumentations/core/transforms_interface.py
volumentations_aucmedi-1.0.1.dist-info/LICENSE
volumentations_aucmedi-1.0.1.dist-info/METADATA
volumentations_aucmedi-1.0.1.dist-info/WHEEL
volumentations_aucmedi-1.0.1.dist-info/top_level.txt
volumentations_aucmedi-1.0.1.dist-info/RECORD
