Metadata-Version: 2.1
Name: volumentations-aucmedi
Version: 1.0.1
Summary: Library for 3D augmentations. Inspired by albumentations.
Home-page: https://github.com/muellerdo/volumentations
Author: Dominik Müller
Author-email: dominik.mueller@informatik.uni-augsburg.de
License: MIT
Platform: UNKNOWN
Classifier: Programming Language :: Python :: 3
Classifier: Programming Language :: Python :: 3.6
Classifier: Programming Language :: Python :: 3.7
Classifier: Programming Language :: Python :: 3.8
Classifier: Operating System :: OS Independent
Classifier: Topic :: Scientific/Engineering :: Artificial Intelligence
Classifier: Topic :: Scientific/Engineering :: Image Recognition
Requires-Python: >=3.6
License-File: LICENSE
Requires-Dist: numpy
Requires-Dist: scikit-image
Requires-Dist: scipy
Requires-Dist: opencv-python
